stdf_utils/__init__.py
stdf_utils/stdf_patch.py
stdf_utils/stdf_per_part.py
stdf_utils/stdf_record.py
stdf_utils/stdf_to_csv.py
stdf_utils/stdf_to_txt.py
stdf_utils/util.py
stdf_utils-0.2.3.dist-info/LICENSE
stdf_utils-0.2.3.dist-info/METADATA
stdf_utils-0.2.3.dist-info/WHEEL
stdf_utils-0.2.3.dist-info/top_level.txt
stdf_utils-0.2.3.dist-info/RECORD
